certbot_dns_directadmin/__init__.py
certbot_dns_directadmin/directadmin.py
certbot_dns_directadmin/dns_directadmin.py
certbot_dns_directadmin-1.0.16.dist-info/LICENSE
certbot_dns_directadmin-1.0.16.dist-info/METADATA
certbot_dns_directadmin-1.0.16.dist-info/WHEEL
certbot_dns_directadmin-1.0.16.dist-info/entry_points.txt
certbot_dns_directadmin-1.0.16.dist-info/RECORD
