Metadata-Version: 2.3
Name: certbot_dns_directadmin
Version: 1.0.16
Summary: Certbot plugin.  Allows completing DNS01 challenge against a DirectAdmin Server
Author: guisea
Author-email: hey@cybercinch.nz
Requires-Python: >3.9.1,<3.12.0
Classifier: Programming Language :: Python :: 3
Classifier: Programming Language :: Python :: 3.10
Classifier: Programming Language :: Python :: 3.11
Requires-Dist: acme (>=2.11.0)
Requires-Dist: certbot (>=2.11.0)
Requires-Dist: cryptography (>=44.0.1)
Requires-Dist: jinja2 (>=3.1.6)
